snekray/__init__.py
snekray/snekray.py
snekray/types/__init__.py
snekray/types/point.py
snekray/types/ptuple.py
snekray/types/vector.py
snekray-0.0.3.dist-info/LICENSE
snekray-0.0.3.dist-info/METADATA
snekray-0.0.3.dist-info/WHEEL
snekray-0.0.3.dist-info/top_level.txt
snekray-0.0.3.dist-info/RECORD
