Metadata-Version: 2.1
Name: snekray
Version: 0.0.3
Summary: A python implementation of The Ray Tracer Challenge
Home-page: https://github.com/vextor22/snekray
Author: Matt Higgins
Author-email: matt@matthiggins.dev
License: UNKNOWN
Project-URL: Bug Tracker, https://github.com/vextor22/snekray/issues
Platform: UNKNOWN
Classifier: Programming Language :: Python :: 3
Classifier: License :: OSI Approved :: GNU General Public License v3 (GPLv3)
Classifier: Operating System :: OS Independent
Requires-Python: >=3.8
License-File: LICENSE
